wspc/__init__.py
wspc/command_line.py
wspc/feature_selection.py
wspc/reader.py
wspc/wspc.py
wspc/model/WSPC_model.pkl
wspc-0.0.6.dist-info/LICENSE
wspc-0.0.6.dist-info/METADATA
wspc-0.0.6.dist-info/WHEEL
wspc-0.0.6.dist-info/entry_points.txt
wspc-0.0.6.dist-info/top_level.txt
wspc-0.0.6.dist-info/RECORD
