Metadata-Version: 2.1
Name: wspc
Version: 0.0.6
Summary: Protein-content-based bacterial pathogenicity classifier
Home-page: https://github.com/shakedna1/wspc_rep
Author: Shaked Naor-Hoffmann & ‪Dina Svetlitsky
Author-email: zivukelson@gmail.com
License: UNKNOWN
Project-URL: Bug Tracker, https://github.com/shakedna1/wspc_rep/issues
Platform: UNKNOWN
Classifier: Programming Language :: Python :: 3
Classifier: License :: OSI Approved :: MIT License
Classifier: Operating System :: OS Independent
Requires-Python: >=3.6
License-File: LICENSE
Requires-Dist: pandas (>=1.2.4)
Requires-Dist: numpy (>=1.20.3)
Requires-Dist: scikit-learn (==0.24.2)
Requires-Dist: scipy (>=1.6.3)
